benstats/__about__.py
benstats/__init__.py
benstats-0.0.3.dist-info/METADATA
benstats-0.0.3.dist-info/WHEEL
benstats-0.0.3.dist-info/licenses/LICENSE.txt
benstats-0.0.3.dist-info/RECORD
