Metadata-Version: 2.1
Name: benstats
Version: 0.0.3
Summary: A Python package for calculating Benford's Law statistics on images
Project-URL: Documentation, https://github.com/unknown/benstats#readme
Project-URL: Issues, https://github.com/unknown/benstats/issues
Project-URL: Source, https://github.com/unknown/benstats
Author-email: gv-sh <gv-sh@outlook.com>, bhaumikdebanshu <bhaumikdebanshu@gmail.com>
License-File: LICENSE.txt
Keywords: benford,image,statistics
Classifier: Development Status :: 4 - Beta
Classifier: Programming Language :: Python
Classifier: Programming Language :: Python :: 3.7
Classifier: Programming Language :: Python :: 3.8
Classifier: Programming Language :: Python :: 3.9
Classifier: Programming Language :: Python :: 3.10
Classifier: Programming Language :: Python :: 3.11
Classifier: Programming Language :: Python :: Implementation :: CPython
Classifier: Programming Language :: Python :: Implementation :: PyPy
Requires-Python: >=3.7
Requires-Dist: matplotlib
Requires-Dist: numpy
Requires-Dist: opencv-python
Requires-Dist: pandas
